illumon/IllumonDb.py
illumon/__init__.py
illumon/constants.py
illumon/java_to_python.py
illumon/jvm_init.py
illumon/python_to_java.py
illumon/start_jvm.py
illumon/iris/__init__.py
illumon/iris/Calendars/__init__.py
illumon/iris/ComboAggregateFactory/__init__.py
illumon/iris/DBTimeUtils/__init__.py
illumon/iris/QueryScope/__init__.py
illumon/iris/TableManagementTools/__init__.py
illumon/iris/TableTools/__init__.py
illumon/iris/plot/__init__.py
illumon/iris/plot/figurewrapper.py
illumon_iris-1.20180803.008.dist-info/METADATA
illumon_iris-1.20180803.008.dist-info/RECORD
illumon_iris-1.20180803.008.dist-info/WHEEL
illumon_iris-1.20180803.008.dist-info/top_level.txt
