Metadata-Version: 2.1
Name: illumon-iris
Version: 1.20180803.008
Summary: Python integrations for Illumon Iris
Home-page: https://www.illumon.com/
Author: Illumon LLC
Author-email: python@illumon.com
License: Apache 2.0
Keywords: Illumon Iris Development
Platform: UNKNOWN
Classifier: Development Status :: 3 - Alpha
Classifier: Intended Audience :: Developers
Classifier: Topic :: Software Development :: Build Tools
Classifier: License :: OSI Approved :: Apache Software License
Classifier: Programming Language :: Python :: 2.7
Requires-Dist: illumon-jpy
